trivialscan/__init__.py
trivialscan/certificate.py
trivialscan/constants.py
trivialscan/exceptions.py
trivialscan/models.py
trivialscan/scores.py
trivialscan/util.py
trivialscan/cli/__init__.py
trivialscan/cli/__main__.py
trivialscan/cli/auth.py
trivialscan/cli/credentials.py
trivialscan/cli/generate.py
trivialscan/cli/info.py
trivialscan/cli/register.py
trivialscan/cli/scan.py
trivialscan/config/__init__.py
trivialscan/config/base.yaml
trivialscan/config/mitre_attack.yaml
trivialscan/config/pci_dss_3.2.1.yaml
trivialscan/config/pci_dss_4.0.yaml
trivialscan/evaluations/__init__.py
trivialscan/evaluations/certificate/__init__.py
trivialscan/evaluations/certificate/caa_present.py
trivialscan/evaluations/certificate/caa_present.yaml
trivialscan/evaluations/certificate/caa_valid.py
trivialscan/evaluations/certificate/caa_valid.yaml
trivialscan/evaluations/certificate/certification_expired.py
trivialscan/evaluations/certificate/certification_expired.yaml
trivialscan/evaluations/certificate/certification_expiring.py
trivialscan/evaluations/certificate/certification_expiring.yaml
trivialscan/evaluations/certificate/certification_version.py
trivialscan/evaluations/certificate/certification_version.yaml
trivialscan/evaluations/certificate/deprecated_dnssec_algorithm.py
trivialscan/evaluations/certificate/deprecated_dnssec_algorithm.yaml
trivialscan/evaluations/certificate/dnssec_present.py
trivialscan/evaluations/certificate/dnssec_present.yaml
trivialscan/evaluations/certificate/dnssec_valid.py
trivialscan/evaluations/certificate/dnssec_valid.yaml
trivialscan/evaluations/certificate/is_self_signed.py
trivialscan/evaluations/certificate/is_self_signed.yaml
trivialscan/evaluations/certificate/known_weak_keys.py
trivialscan/evaluations/certificate/known_weak_keys.yaml
trivialscan/evaluations/certificate/known_weak_signature_algorithm.py
trivialscan/evaluations/certificate/known_weak_signature_algorithm.yaml
trivialscan/evaluations/certificate/leaf_ca.py
trivialscan-0.5.17.dist-info/LICENSE
trivialscan-0.5.17.dist-info/METADATA
trivialscan-0.5.17.dist-info/WHEEL
trivialscan-0.5.17.dist-info/entry_points.txt
trivialscan-0.5.17.dist-info/top_level.txt
trivialscan-0.5.17.dist-info/RECORD
