Metadata-Version: 2.1
Name: trivialscan
Version: 0.5.17
Summary: Validate the security of your TLS connections so that they deserve your trust.
Author-email: Christopher Langton <chris@trivialsec.com>
License: GNU GENERAL PUBLIC LICENSE
Project-URL: Homepage, https://www.trivialsec.com
Project-URL: Bug Tracker, https://gitlab.com/trivialsec/trivialscan/-/issues
Classifier: Programming Language :: Python :: 3
Requires-Python: >=3.9
License-File: LICENSE
Requires-Dist: cryptography (>=2.0)
Requires-Dist: certifi
Requires-Dist: asn1crypto
Requires-Dist: pyOpenSSL
Requires-Dist: rich
Requires-Dist: validators
Requires-Dist: pydantic
Requires-Dist: idna
Requires-Dist: tlstrust (>=2.8.0)
Requires-Dist: certvalidator
Requires-Dist: dnspython
Requires-Dist: h2 (>=4.1.0)
Requires-Dist: hpack (>=4.0.0)
Requires-Dist: oscrypto
Requires-Dist: requests (>=2.27.1)
Requires-Dist: urllib3 (>=1.26.9)
Requires-Dist: appdirs (>=1.4.4)
Requires-Dist: attrs (>=21.4.0)
Requires-Dist: cattrs (>=1.10.0)
Requires-Dist: requests-cache (>=0.9.4)
Requires-Dist: url-normalize (>=1.4.3)
Requires-Dist: retry
Requires-Dist: tldextract
Requires-Dist: pyyaml
Requires-Dist: art
Requires-Dist: keyring (>=23.6.0)
Requires-Dist: deepdiff
Requires-Dist: pycryptodome (>=3.15.0)
Requires-Dist: beautifulsoup4 (>=4.11.1)
Requires-Dist: requests-toolbelt (>=0.9.1)
